{
    "status": "success",
    "data": {
        "summary": {
            "all": {
                "kills": 1.0,
                "matchXp": 0.0,
                "lootTimePlayed": 0.0,
                "averageSpeedDuringMatch": 0.0,
                "scoreXp": 0.0,
                "numUavCalled": 0.0,
                "accuracy": 0.22535211267605634,
                "losses": 0.0,
                "avgLifeTime": 691823.5294117647,
                "timePlayedMoving": 0.0,
                "totalDistanceTravelled": 0.0,
                "totalXp": 210.0,
                "score": 0.0,
                "challengesCompletedCount": 0.0,
                "headshots": 0.0,
                "assists": 0.0,
                "misses": 55.0,
                "killsPerGame": 0.1111111111111111,
                "scorePerMinute": 0.0,
                "objectiveTime": 0.0,
                "killsDenied": 0.0,
                "deaths": 8.0,
                "wins": 0.0,
                "kdRatio": 0.125,
                "killsConfirmed": 0.0,
                "totalTimePlayedS": 1975.0,
                "hits": 16.0,
                "timePlayed": 1.1761E7,
                "teamkills": 0.0,
                "weaponPickupsCount": 0.0,
                "headshotPercentage": 0.0,
                "matchesPlayed": 9.0,
                "suicides": 0.0,
                "lootXpEarned": 0.0,
                "timePlayedAlive": 0.0,
                "escortTime": 0.0
            },
            "warzone_solo": {
                "kills": 1.0,
                "matchXp": 0.0,
                "lootTimePlayed": 0.0,
                "averageSpeedDuringMatch": 0.0,
                "scoreXp": 0.0,
                "numUavCalled": 0.0,
                "accuracy": 0.22535211267605634,
                "losses": 0.0,
                "avgLifeTime": 691823.5294117647,
                "timePlayedMoving": 0.0,
                "totalDistanceTravelled": 0.0,
                "totalXp": 210.0,
                "score": 0.0,
                "challengesCompletedCount": 0.0,
                "headshots": 0.0,
                "assists": 0.0,
                "misses": 55.0,
                "killsPerGame": 0.1111111111111111,
                "scorePerMinute": 0.0,
                "objectiveTime": 0.0,
                "killsDenied": 0.0,
                "deaths": 8.0,
                "wins": 0.0,
                "kdRatio": 0.125,
                "scorePerGame": 0.0,
                "killsConfirmed": 0.0,
                "totalTimePlayedS": 1975.0,
                "hits": 16.0,
                "timePlayed": 1.1761E7,
                "teamkills": 0.0,
                "weaponPickupsCount": 0.0,
                "headshotPercentage": 0.0,
                "matchesPlayed": 9.0,
                "suicides": 0.0,
                "lootXpEarned": 0.0,
                "timePlayedAlive": 0.0,
                "escortTime": 0.0
            }
        },
        "matches": [
            {
                "utcStartSeconds": 1550728282,
                "utcEndSeconds": 1550729652,
                "map": "wz_open_skyscrapers",
                "mode": "warzone_solo",
                "matchID": "9552767799719157356",
                "duration": 1370000,
                "playlistName": "playlist/warzone_open_sky_solo",
                "version": 1,
                "gameType": "wz",
                "playerCount": 0,
                "playerStats": {
                    "kills": 0.0,
                    "matchXp": 0.0,
                    "lootTimePlayed": 0.0,
                    "averageSpeedDuringMatch": 0.0,
                    "scoreXp": 0.0,
                    "numUavCalled": 0.0,
                    "losses": 0.0,
                    "timePlayedMoving": 0.0,
                    "totalDistanceTravelled": 0.0,
                    "totalXp": 100.0,
                    "startXp": 200.0,
                    "score": 0.0,
                    "challengesCompletedCount": 0.0,
                    "headshots": 0.0,
                    "endRank": 0.0,
                    "assists": 0.0,
                    "gamesPlayed": 0.0,
                    "misses": 2.0,
                    "objectiveTime": 0.0,
                    "killsDenied": 0.0,
                    "deaths": 1.0,
                    "wins": 0.0,
                    "percentageOfTimeMoving": 0.0,
                    "averageKillDistance": 0.0,
                    "killsConfirmed": 0.0,
                    "totalTimePlayedS": 394.0,
                    "prestige": 0.0,
                    "playerPlacement": 48.0,
                    "hits": 0.0,
                    "endXp": 300.0,
                    "teamkills": 0.0,
                    "weaponPickupsCount": 0.0,
                    "suicides": 0.0,
                    "lootXpEarned": 0.0,
                    "timePlayedAlive": 0.0,
                    "startRank": 0.0,
                    "teamPlacement": 48.0,
                    "position": 0.0,
                    "escortTime": 0.0
                },
                "player": null,
                "teamCount": 0,
                "rankedTeams": null,
                "draw": false,
                "privateMatch": false
            },
            {
                "utcStartSeconds": 1550727672,
                "utcEndSeconds": 1550729049,
                "map": "wz_open_skyscrapers",
                "mode": "warzone_solo",
                "matchID": "14774173825512615581",
                "duration": 1376800,
                "playlistName": "playlist/warzone_open_sky_solo",
                "version": 1,
                "gameType": "wz",
                "playerCount": 0,
                "playerStats": {
                    "kills": 0.0,
                    "matchXp": 0.0,
                    "lootTimePlayed": 0.0,
                    "averageSpeedDuringMatch": 0.0,
                    "scoreXp": 0.0,
                    "numUavCalled": 0.0,
                    "losses": 0.0,
                    "timePlayedMoving": 0.0,
                    "totalDistanceTravelled": 0.0,
                    "totalXp": 100.0,
                    "startXp": 100.0,
                    "score": 0.0,
                    "challengesCompletedCount": 0.0,
                    "headshots": 0.0,
                    "endRank": 0.0,
                    "assists": 0.0,
                    "gamesPlayed": 0.0,
                    "misses": 26.0,
                    "objectiveTime": 0.0,
                    "killsDenied": 0.0,
                    "deaths": 1.0,
                    "wins": 0.0,
                    "percentageOfTimeMoving": 0.0,
                    "averageKillDistance": 0.0,
                    "killsConfirmed": 0.0,
                    "totalTimePlayedS": 433.0,
                    "prestige": 0.0,
                    "playerPlacement": 43.0,
                    "hits": 0.0,
                    "endXp": 200.0,
                    "teamkills": 0.0,
                    "weaponPickupsCount": 0.0,
                    "suicides": 0.0,
                    "lootXpEarned": 0.0,
                    "timePlayedAlive": 0.0,
                    "startRank": 0.0,
                    "teamPlacement": 43.0,
                    "position": 0.0,
                    "escortTime": 0.0
                },
                "player": null,
                "teamCount": 0,
                "rankedTeams": null,
                "draw": false,
                "privateMatch": false
            },
            {
                "utcStartSeconds": 1542777817,
                "utcEndSeconds": 1542779110,
                "map": "wz_open_skyscrapers",
                "mode": "warzone_solo",
                "matchID": "1268189356955862272",
                "duration": 1293300,
                "playlistName": "playlist/warzone_open_sky_solo",
                "version": 1,
                "gameType": "wz",
                "playerCount": 0,
                "playerStats": {
                    "kills": 0.0,
                    "playerBody": 0.0,
                    "matchXp": 0.0,
                    "lootTimePlayed": 0.0,
                    "averageSpeedDuringMatch": 0.0,
                    "scoreXp": 0.0,
                    "playerHead": 0.0,
                    "numUavCalled": 0.0,
                    "losses": 0.0,
                    "timePlayedMoving": 0.0,
                    "totalDistanceTravelled": 0.0,
                    "totalXp": 0.0,
                    "startXp": 10.0,
                    "score": 0.0,
                    "challengesCompletedCount": 0.0,
                    "headshots": 0.0,
                    "endRank": 0.0,
                    "assists": 0.0,
                    "gamesPlayed": 0.0,
                    "misses": 2.0,
                    "objectiveTime": 0.0,
                    "killsDenied": 0.0,
                    "deaths": 1.0,
                    "wins": 0.0,
                    "percentageOfTimeMoving": 0.0,
                    "averageKillDistance": 0.0,
                    "killsConfirmed": 0.0,
                    "totalTimePlayedS": 208.0,
                    "prestige": 0.0,
                    "playerPlacement": 50.0,
                    "hits": 2.0,
                    "endXp": 10.0,
                    "teamkills": 0.0,
                    "weaponPickupsCount": 0.0,
                    "suicides": 0.0,
                    "lootXpEarned": 0.0,
                    "timePlayedAlive": 0.0,
                    "startRank": 0.0,
                    "teamPlacement": 50.0,
                    "position": 0.0,
                    "escortTime": 0.0
                },
                "player": null,
                "teamCount": 0,
                "rankedTeams": null,
                "draw": false,
                "privateMatch": false
            },
            {
                "utcStartSeconds": 1539656234,
                "utcEndSeconds": 1539657458,
                "map": "wz_open_skyscrapers",
                "mode": "warzone_solo",
                "matchID": "7908082993835920359",
                "duration": 1224000,
                "playlistName": "playlist/warzone_open_sky_solo",
                "version": 1,
                "gameType": "wz",
                "playerCount": 0,
                "playerStats": {
                    "kills": 0.0,
                    "playerBody": 0.0,
                    "matchXp": 0.0,
                    "lootTimePlayed": 0.0,
                    "averageSpeedDuringMatch": 0.0,
                    "scoreXp": 0.0,
                    "playerHead": 0.0,
                    "numUavCalled": 0.0,
                    "losses": 0.0,
                    "timePlayedMoving": 0.0,
                    "totalDistanceTravelled": 0.0,
                    "totalXp": 0.0,
                    "startXp": 10.0,
                    "score": 0.0,
                    "challengesCompletedCount": 0.0,
                    "headshots": 0.0,
                    "endRank": 0.0,
                    "assists": 0.0,
                    "gamesPlayed": 0.0,
                    "misses": 1.0,
                    "objectiveTime": 0.0,
                    "killsDenied": 0.0,
                    "deaths": 1.0,
                    "wins": 0.0,
                    "percentageOfTimeMoving": 0.0,
                    "averageKillDistance": 0.0,
                    "killsConfirmed": 0.0,
                    "totalTimePlayedS": 134.0,
                    "prestige": 0.0,
                    "playerPlacement": 71.0,
                    "hits": 0.0,
                    "endXp": 10.0,
                    "teamkills": 0.0,
                    "weaponPickupsCount": 0.0,
                    "suicides": 0.0,
                    "lootXpEarned": 0.0,
                    "timePlayedAlive": 0.0,
                    "startRank": 0.0,
                    "teamPlacement": 71.0,
                    "position": 0.0,
                    "escortTime": 0.0
                },
                "player": null,
                "teamCount": 0,
                "rankedTeams": null,
                "draw": false,
                "privateMatch": false
            },
            {
                "utcStartSeconds": 1539655984,
                "utcEndSeconds": 1539657257,
                "map": "wz_open_skyscrapers",
                "mode": "warzone_solo",
                "matchID": "13910395152135104113",
                "duration": 1272650,
                "playlistName": "playlist/warzone_open_sky_solo",
                "version": 1,
                "gameType": "wz",
                "playerCount": 0,
                "playerStats": {
                    "kills": 0.0,
                    "playerBody": 0.0,
                    "matchXp": 0.0,
                    "lootTimePlayed": 0.0,
                    "averageSpeedDuringMatch": 0.0,
                    "scoreXp": 0.0,
                    "playerHead": 0.0,
                    "numUavCalled": 0.0,
                    "losses": 0.0,
                    "timePlayedMoving": 0.0,
                    "totalDistanceTravelled": 0.0,
                    "totalXp": 0.0,
                    "startXp": 10.0,
                    "score": 0.0,
                    "challengesCompletedCount": 0.0,
                    "headshots": 0.0,
                    "endRank": 0.0,
                    "assists": 0.0,
                    "gamesPlayed": 0.0,
                    "misses": 0.0,
                    "objectiveTime": 0.0,
                    "killsDenied": 0.0,
                    "deaths": 1.0,
                    "wins": 0.0,
                    "percentageOfTimeMoving": 0.0,
                    "averageKillDistance": 0.0,
                    "killsConfirmed": 0.0,
                    "totalTimePlayedS": 51.0,
                    "prestige": 0.0,
                    "playerPlacement": 76.0,
                    "hits": 0.0,
                    "endXp": 10.0,
                    "teamkills": 0.0,
                    "weaponPickupsCount": 0.0,
                    "suicides": 0.0,
                    "lootXpEarned": 0.0,
                    "timePlayedAlive": 0.0,
                    "startRank": 0.0,
                    "teamPlacement": 76.0,
                    "position": 0.0,
                    "escortTime": 0.0
                },
                "player": null,
                "teamCount": 0,
                "rankedTeams": null,
                "draw": false,
                "privateMatch": false
            },
            {
                "utcStartSeconds": 1539655469,
                "utcEndSeconds": 1539656753,
                "map": "wz_open_skyscrapers",
                "mode": "warzone_solo",
                "matchID": "12162590307392955334",
                "duration": 1283600,
                "playlistName": "playlist/warzone_open_sky_solo",
                "version": 1,
                "gameType": "wz",
                "playerCount": 0,
                "playerStats": {
                    "kills": 1.0,
                    "playerBody": 0.0,
                    "matchXp": 0.0,
                    "lootTimePlayed": 0.0,
                    "averageSpeedDuringMatch": 0.0,
                    "scoreXp": 0.0,
                    "playerHead": 0.0,
                    "numUavCalled": 0.0,
                    "losses": 0.0,
                    "timePlayedMoving": 0.0,
                    "totalDistanceTravelled": 0.0,
                    "totalXp": 10.0,
                    "startXp": 0.0,
                    "score": 0.0,
                    "challengesCompletedCount": 0.0,
                    "headshots": 0.0,
                    "endRank": 0.0,
                    "assists": 0.0,
                    "gamesPlayed": 0.0,
                    "misses": 9.0,
                    "objectiveTime": 0.0,
                    "killsDenied": 0.0,
                    "deaths": 1.0,
                    "wins": 0.0,
                    "percentageOfTimeMoving": 0.0,
                    "averageKillDistance": 0.0,
                    "killsConfirmed": 0.0,
                    "totalTimePlayedS": 334.0,
                    "prestige": 0.0,
                    "playerPlacement": 38.0,
                    "hits": 10.0,
                    "endXp": 10.0,
                    "teamkills": 0.0,
                    "weaponPickupsCount": 0.0,
                    "suicides": 0.0,
                    "lootXpEarned": 0.0,
                    "timePlayedAlive": 0.0,
                    "startRank": 0.0,
                    "teamPlacement": 38.0,
                    "position": 0.0,
                    "escortTime": 0.0
                },
                "player": null,
                "teamCount": 0,
                "rankedTeams": null,
                "draw": false,
                "privateMatch": false
            },
            {
                "utcStartSeconds": 1539574312,
                "utcEndSeconds": 1539575664,
                "map": "wz_open_skyscrapers",
                "mode": "warzone_solo",
                "matchID": "8500269844096658191",
                "duration": 1352250,
                "playlistName": "playlist/warzone_open_sky_solo",
                "version": 1,
                "gameType": "wz",
                "playerCount": 0,
                "playerStats": {
                    "kills": 0.0,
                    "playerBody": 0.0,
                    "matchXp": 0.0,
                    "lootTimePlayed": 0.0,
                    "averageSpeedDuringMatch": 0.0,
                    "scoreXp": 0.0,
                    "playerHead": 0.0,
                    "numUavCalled": 0.0,
                    "losses": 0.0,
                    "timePlayedMoving": 0.0,
                    "totalDistanceTravelled": 0.0,
                    "totalXp": 0.0,
                    "startXp": 0.0,
                    "score": 0.0,
                    "challengesCompletedCount": 0.0,
                    "headshots": 0.0,
                    "endRank": 0.0,
                    "assists": 0.0,
                    "gamesPlayed": 0.0,
                    "misses": 0.0,
                    "objectiveTime": 0.0,
                    "killsDenied": 0.0,
                    "deaths": 1.0,
                    "wins": 0.0,
                    "percentageOfTimeMoving": 0.0,
                    "averageKillDistance": 0.0,
                    "killsConfirmed": 0.0,
                    "totalTimePlayedS": 85.0,
                    "prestige": 0.0,
                    "playerPlacement": 83.0,
                    "hits": 0.0,
                    "endXp": 0.0,
                    "teamkills": 0.0,
                    "weaponPickupsCount": 0.0,
                    "suicides": 0.0,
                    "lootXpEarned": 0.0,
                    "timePlayedAlive": 0.0,
                    "startRank": 0.0,
                    "teamPlacement": 83.0,
                    "position": 0.0,
                    "escortTime": 0.0
                },
                "player": null,
                "teamCount": 0,
                "rankedTeams": null,
                "draw": false,
                "privateMatch": false
            },
            {
                "utcStartSeconds": 1539492281,
                "utcEndSeconds": 1539493509,
                "map": "wz_open_skyscrapers",
                "mode": "warzone_solo",
                "matchID": "10773025751646952167",
                "duration": 1228250,
                "playlistName": "playlist/warzone_open_sky_solo",
                "version": 1,
                "gameType": "wz",
                "playerCount": 0,
                "playerStats": {
                    "kills": 0.0,
                    "playerBody": 0.0,
                    "matchXp": 0.0,
                    "lootTimePlayed": 0.0,
                    "averageSpeedDuringMatch": 0.0,
                    "scoreXp": 0.0,
                    "playerHead": 0.0,
                    "numUavCalled": 0.0,
                    "losses": 0.0,
                    "timePlayedMoving": 0.0,
                    "totalDistanceTravelled": 0.0,
                    "totalXp": 0.0,
                    "startXp": 0.0,
                    "score": 0.0,
                    "challengesCompletedCount": 0.0,
                    "headshots": 0.0,
                    "endRank": 0.0,
                    "assists": 0.0,
                    "gamesPlayed": 0.0,
                    "misses": 15.0,
                    "objectiveTime": 0.0,
                    "killsDenied": 0.0,
                    "deaths": 1.0,
                    "wins": 0.0,
                    "percentageOfTimeMoving": 0.0,
                    "averageKillDistance": 0.0,
                    "killsConfirmed": 0.0,
                    "totalTimePlayedS": 336.0,
                    "prestige": 0.0,
                    "playerPlacement": 42.0,
                    "hits": 4.0,
                    "endXp": 0.0,
                    "teamkills": 0.0,
                    "weaponPickupsCount": 0.0,
                    "suicides": 0.0,
                    "lootXpEarned": 0.0,
                    "timePlayedAlive": 0.0,
                    "startRank": 0.0,
                    "teamPlacement": 42.0,
                    "position": 0.0,
                    "escortTime": 0.0
                },
                "player": null,
                "teamCount": 0,
                "rankedTeams": null,
                "draw": false,
                "privateMatch": false
            },
            {
                "utcStartSeconds": 1539492176,
                "utcEndSeconds": 1539493536,
                "map": "wz_open_skyscrapers",
                "mode": "warzone_solo",
                "matchID": "18045467364002519812",
                "duration": 1360150,
                "playlistName": "playlist/warzone_open_sky_solo",
                "version": 1,
                "gameType": "wz",
                "playerCount": 0,
                "playerStats": {
                    "kills": 0.0,
                    "playerBody": 0.0,
                    "matchXp": 0.0,
                    "lootTimePlayed": 0.0,
                    "averageSpeedDuringMatch": 0.0,
                    "scoreXp": 0.0,
                    "playerHead": 0.0,
                    "numUavCalled": 0.0,
                    "losses": 0.0,
                    "timePlayedMoving": 0.0,
                    "totalDistanceTravelled": 0.0,
                    "totalXp": 0.0,
                    "startXp": 0.0,
                    "score": 0.0,
                    "challengesCompletedCount": 0.0,
                    "headshots": 0.0,
                    "endRank": 0.0,
                    "assists": 0.0,
                    "gamesPlayed": 0.0,
                    "misses": 0.0,
                    "objectiveTime": 0.0,
                    "killsDenied": 0.0,
                    "deaths": 0.0,
                    "wins": 0.0,
                    "percentageOfTimeMoving": 0.0,
                    "averageKillDistance": 0.0,
                    "killsConfirmed": 0.0,
                    "totalTimePlayedS": 0.0,
                    "prestige": 0.0,
                    "playerPlacement": 0.0,
                    "hits": 0.0,
                    "endXp": 0.0,
                    "teamkills": 0.0,
                    "weaponPickupsCount": 0.0,
                    "suicides": 0.0,
                    "lootXpEarned": 0.0,
                    "timePlayedAlive": 0.0,
                    "startRank": 0.0,
                    "teamPlacement": null,
                    "position": 0.0,
                    "escortTime": 0.0
                },
                "player": null,
                "teamCount": 0,
                "rankedTeams": null,
                "draw": false,
                "privateMatch": false
            }
        ]
    }
}